Surreal-0.2.1.dist-info/METADATA
Surreal-0.2.1.dist-info/RECORD
Surreal-0.2.1.dist-info/WHEEL
Surreal-0.2.1.dist-info/entry_points.txt
Surreal-0.2.1.dist-info/top_level.txt
surreal/__init__.py
surreal/sample_surreal.yml
surreal/agent/__init__.py
surreal/agent/action_noise.py
surreal/agent/base.py
surreal/agent/ddpg_agent.py
surreal/agent/param_noise.py
surreal/agent/ppo_agent.py
surreal/agent/q_agent.py
surreal/distributed/__init__.py
surreal/distributed/data_fetcher.py
surreal/distributed/exp_collector.py
surreal/distributed/exp_sender.py
surreal/distributed/module_dict.py
surreal/distributed/parameter_server.py
surreal/env/__init__.py
surreal/env/atari_names.py
surreal/env/atari_wrappers.py
surreal/env/atari_wrappers_deprecated.py
surreal/env/base.py
surreal/env/dm_wrapper.py
surreal/env/exp_sender_wrapper.py
surreal/env/make_env.py
surreal/env/monitor.py
surreal/env/video_env.py
surreal/env/wrapper.py
surreal/env/builders/__init__.py
surreal/kube/__init__.py
surreal/kube/surreal_kube.py
surreal/launch/__init__.py
surreal/launch/build_images.py
surreal/launch/command_generator.py
surreal/launch/launcher.py
surreal/launch/setup_network.py
surreal/launch/symphony_containerized.py
surreal/learner/__init__.py
surreal/learner/aggregator.py
surreal/learner/base.py
surreal/learner/ddpg.py
surreal/learner/dqn.py
surreal/learner/ppo.py
surreal/main/__init__.py
surreal/main/ddpg_configs.py
surreal/main/generate_default_config.py
surreal/main/ppo_configs.py
surreal/main/ppo_configs_cheetah.py
surreal/main/ppo_configs_hopper.py
surreal/main/rollout.py
surreal/model/__init__.py
surreal/model/ddpg_net.py
surreal/model/ppo_net.py
surreal/model/q_net.py
surreal/model/reward_filter.py
surreal/model/z_filter.py
surreal/model/model_builders/__init__.py
surreal/model/model_builders/builders.py
surreal/model/model_builders/head_builder.py
surreal/model/model_builders/torso_builder.py
surreal/replay/__init__.py
surreal/replay/base.py
surreal/replay/dummy_replay.py
surreal/replay/fifo_replay.py
surreal/replay/prioritized_replay.py
surreal/replay/segment_tree.py
