Metadata-Version: 2.1
Name: Surreal
Version: 0.2.1
Summary: Stanford University Repository for Reinforcement Algorithms
Home-page: http://github.com/StanfordVL/Surreal
Author: Stanford Vision and Learning Lab
Author-email: UNKNOWN
License: GPLv3
Keywords: Reinforcement Learning,Deep Learning,Distributed Computing
Platform: UNKNOWN
Classifier: Development Status :: 4 - Beta
Classifier: Topic :: Scientific/Engineering :: Artificial Intelligence
Classifier: Environment :: Console
Classifier: Programming Language :: Python :: 3
Requires-Dist: gym
Requires-Dist: robosuite
Requires-Dist: mujoco-py (<1.50.2,>=1.50.1)
Requires-Dist: tabulate
Requires-Dist: tensorflow
Requires-Dist: tensorboardX
Requires-Dist: imageio
Requires-Dist: pygame
Requires-Dist: benedict
Requires-Dist: nanolog
Requires-Dist: psutil
Requires-Dist: tabulate
Requires-Dist: imageio
Requires-Dist: caraml (>=0.10.0)
Requires-Dist: symphony (>=0.9.1)
Requires-Dist: torchx (==0.9)
Requires-Dist: tensorplex
Requires-Dist: cloudwise (>=0.1.1)
Requires-Dist: Cython (<0.29)
